{
    "title": "中華民國 67年國慶總統祝詞 - 蔣經國總統",
    "系統序號": "00055305",
    "隸屬全宗": "005",
    "資料集": "總統文告與講詞",
    "資料類型": "國慶講詞",
    "卷/案/冊號": "蔣經國總統文告",
    "典藏號": "PSPCH0000062",
    "日期描述": "中華民國67年10月10日 ( 國慶日 )",
    "日期範圍-起": "1978-10-10",
    "日期範圍-迄": "1978-10-10",
    "系列階層": "總統文告與講詞/國慶日/1978民國67年",
    "標題": "中華民國 67年國慶總統祝詞 - 蔣經國總統",
    "相關人名": "蔣經國",
    "關鍵字詞": "歲時節慶、國慶日",
    "備註": "第六任總統",
    "資料來源": "政府公報資訊網",
    "匯入來源": "政府公報資訊網",
    "資料密等": "普通",
    "引用資訊": "政府公報資訊網",
    "content": "\n\t\t\t\t　　中華民國的雙十國慶，是我全國同胞無比光榮、無限歡欣的日子，這個日子代表着國家一頁又一頁光輝與苦難交織的歷史，也反映了中華民族堅忍剛毅、正氣浩然的崇高性格。<br><br>　　六十七年前的今天，&nbsp;&nbsp;國父秉大仁大智大勇，結合無數革命志士，為救國救民，歷盡艱辛，締造了亞洲第一個民主共和國家。但是內憂外患，使國家仍無寧日，總統&nbsp;&nbsp;蔣公繼志承烈，以大擔當、大毅力、大無畏的獻身精神，領導國民革命，堅苦卓絕，終於完成北伐、抗日、行憲等偉大使命，也為反共復國立下堅強不拔的復興基地。這些史實，充分說明了中華兒女對國家民族責任的自覺，對天下興亡的勇敢承擔，也象徵着仁者無敵、正義必勝的必然結果。因之，雙十國慶的意義實在是多重的，那不僅帶給我們節日的歡慶，也使我們得到責任的啟示，行動的鞭策和成功的鼓舞。尤其在這北伐統一五十周年的今年國慶，更增加我們對這體認的深刻激勵！<br><br>　　今天敵人共匪的暴政還沒有消滅，自由世界的姑息逆流也還未消失，我們國家民族又面臨着較前更為嚴厲的考驗，而迎接這一考驗的重責大任，正落在我們海內海外所有愛自由、愛民主、反共產、反奴役的每一個中華兒女的肩上，凡是有血性、有正義的炎黃子孫，必當踏着先賢先烈愈挫愈奮、勇往直前的足跡，以反共復國為己任，為這神聖使命而奉獻一切心力！<br><br>　　現階段國民革命的總目標，是實踐三民主義，光復大陸國土，把我們復興基地仁政建設的規模和成果，推展到故國河山的每一角落，使所有中國同胞都能共享三民主義自由民主、安和樂利的生活，都位重獲中華文化的精神力量。我們深信，只要大家歸向在這一總目標之下，齊一意志，堅定信念，親愛精誠，團結奮鬥，有志者，事竟成！<br><br>　　我們誓願要使青天白白永遠照耀出雙十國慶的萬丈光芒，更要使未來世代的中華民族永遠康樂富強。讓我們一同祝福中華民國國運昌隆！也讓我們來齊聲高呼：<br><br>　　三民主義萬歲！<br><br>　　中華民國萬歲！\t\t\t\t"
}