{
    "title": "中華民國 77年元旦總統祝詞 - 蔣經國總統",
    "系統序號": "00055324",
    "隸屬全宗": "005",
    "資料集": "總統文告與講詞",
    "資料類型": "元旦文告",
    "卷/案/冊號": "蔣經國總統文告",
    "典藏號": "PSPCH0000081",
    "日期描述": "中華民國77年01月01日 ( 元旦 )",
    "日期範圍-起": "1988-01-01",
    "日期範圍-迄": "1988-01-01",
    "系列階層": "總統文告與講詞/元旦/1988民國77年",
    "標題": "中華民國 77年元旦總統祝詞 - 蔣經國總統",
    "相關人名": "蔣經國",
    "關鍵字詞": "歲時節慶、元旦",
    "備註": "第七任總統",
    "資料來源": "政府公報資訊網",
    "匯入來源": "政府公報資訊網",
    "資料密等": "普通",
    "引用資訊": "政府公報資訊網",
    "content": "\n\t\t\t\t親愛的父老兄弟姐妹們：<br><br>　　中華民國七十七年元旦，在大家歡欣鼓舞中到來，展現在我們眼前的、也是海內外瞩望的，將是又一個繁榮進步、生氣勃勃的年頭。開國史實的輝煌燦爛和復興基地的欣欣向榮，前後輝映，照耀出中華民國的前途光明；生聚教訓與精誠團結凝成的力量，堅定了必勝必成的信念。當前，正是我們握機造勢、乘時奮起，再創新運的時刻。&nbsp;<br><br>　　七十六年來的艱難國步，真是榮辱交織、血淚交併；我們追求中國自由平等的大業，再三受阻於軍閥的誤國、列強的覬覦、與共黨的叛亂。但是，三民主義的精華久而彌新，復興基地的建設日與月盛，歷史終將證明，「得民者昌」、「暴政必亡」，永遠是經得起考驗的真理。<br><br>　　中國的未來，操在全體中國人自己手中。中共暴政迫使中國人民遭受了空前的苦難，反共救國已是全民的心聲，也是唯一的出路。誠然，中興大業任重道遠，但形勢已十分明顯，我們樂觀開朗，滿懷信心，&nbsp;因為：<br><br>　　海內外全體中國人均已清楚看到，台灣復興基地致力三民主義建設的豐碩成果，已為中國的未來塑造了成功的模式，一致確認，唯有遵循自由、民主、憲政的大道，統一在以中華文化為基礎的三民主義之下，才是民族發展、國家富強和國民福祉的最好保證。&nbsp;<br><br>　　大陸同胞都已了解，經過了將近四十年的共黨極權統治，他們不僅喪失了基本權利與自由，至今連民生食品還要實施「配購」，他們的苦難，大陸的貧困，完全是中共的虐政所造成，因之大家普遍認定，唯有中國人一致奮起，推翻共產專政，才是自救救國的根本之計。&nbsp;<br><br>　　自由世界也都認識，唯有中華民國的奮鬥成功，才是促使中國大陸重返民主陣營的主要力量，才是促進亞洲與世界和平的重要關鍵。<br><br>　　親愛的父老兄弟姐妹們，海峽的阻隔，不能切斷中華兒女的血脈相連，時間的消逝，也不能減少我們統&nbsp;一中國的信念。&nbsp;&nbsp;國父與先總統&nbsp;&nbsp;蔣公為中國力圖富強康樂的苦心孤詣，永遠在我們的心中縈懷。讓我們同心協力，加速民主政治與自由經濟的建設，高舉三民主義的大旗，迎接大陸重光的早日來臨。讓我們一齊高呼：<br><br>　　三民主義萬歲！<br><br>　　中華民國萬歲！\t\t\t\t"
}